sapy_script/SAP.py
sapy_script/Session.py
sapy_script/__init__.py
sapy_script/__main__.py
sapy_script-1.0.1.dist-info/METADATA
sapy_script-1.0.1.dist-info/RECORD
sapy_script-1.0.1.dist-info/WHEEL
sapy_script-1.0.1.dist-info/top_level.txt
